api_cli.py
dsframework/__init__.py
dsframework/base/__init__.py
dsframework/base/batch/__init__.py
dsframework/base/batch/dag_base.py
dsframework/base/batch/pipeline_stage_base.py
dsframework/base/batch/workflow_base.py
dsframework/base/cloud_eval/__init__.py
dsframework/base/cloud_eval/cloud_eval_client_base.py
dsframework/base/cloud_eval/worker.py
dsframework/base/common/__init__.py
dsframework/base/common/component.py
dsframework/base/common/functions.py
dsframework/base/common/object.py
dsframework/base/common/regex_handler.py
dsframework/base/logger/__init__.py
dsframework/base/logger/dsflogger.py
dsframework/base/logger/pubsub_handler.py
dsframework/base/pipeline/__init__.py
dsframework/base/pipeline/pipeline.py
dsframework/base/pipeline/artifacts/__init__.py
dsframework/base/pipeline/artifacts/shared_artifacts.py
dsframework/base/pipeline/forcers/__init__.py
dsframework/base/pipeline/postprocessor/__init__.py
dsframework/base/pipeline/postprocessor/postprocess.py
dsframework/base/pipeline/predictables/__init__.py
dsframework/base/pipeline/predictables/predictable.py
dsframework/base/pipeline/predictors/__init__.py
dsframework/base/pipeline/preprocessor/__init__.py
dsframework/base/pipeline/preprocessor/preprocess.py
dsframework/base/server/__init__.py
dsframework/base/server/cache/__init__.py
dsframework/base/server/cache/cache.py
dsframework/base/server/cache/cache_utils.py
dsframework/base/server/cache/redis_cache.py
dsframework/base/server/tests/__init__.py
dsframework/base/server/tests/test_cache.py
dsframework/base/server/tests/test_cache_utils.py
dsframework/base/testable/__init__.py
dsframework/base/tester/__init__.py
dsframework/base/tester/evaluator_logic.py
dsframework/base/tester/tester_logic.py
dsframework/base/tester/unit_test_generator/__init__.py
dsframework/base/tester/unit_test_generator/generate_unit_test.py
dsframework/base/tester/unit_test_generator/json_encoder.py
dsframework/base/tester/unit_test_generator/read_files.py
dsframework-0.4.5.dist-info/METADATA
dsframework-0.4.5.dist-info/WHEEL
dsframework-0.4.5.dist-info/entry_points.txt
dsframework-0.4.5.dist-info/top_level.txt
dsframework-0.4.5.dist-info/RECORD
