Metadata-Version: 2.4
Name: dsFramework
Version: 0.4.5
Summary: Data science framework library
Author: oribrau@gmail.com
License: MIT
Requires-Dist: dvc[gs,s3]==2.45.1
Requires-Dist: click==8.0.1
Requires-Dist: pydantic==2.10.5
Requires-Dist: tldextract==3.1.2
Requires-Dist: uvicorn==0.23.2
Requires-Dist: gunicorn==23.0.0
Requires-Dist: fastapi==0.115.6
Requires-Dist: requests==2.31.0
Requires-Dist: Unidecode==1.3.7
Requires-Dist: python-json-logger==2.0.1
Requires-Dist: google-api-python-client==2.21.0
Requires-Dist: oauth2client==4.1.3
Requires-Dist: pandas<3.0.0,>=2.2.3
Requires-Dist: logdecorator==2.2
Requires-Dist: ujson==5.11.0
Requires-Dist: redis==3.5.3
Requires-Dist: fastapi_utils==0.7.0
Requires-Dist: google-cloud-pubsub==2.13.11
Dynamic: author
Dynamic: description
Dynamic: description-content-type
Dynamic: license
Dynamic: requires-dist
Dynamic: summary
